plotbin/__init__.py
plotbin/display_bins.py
plotbin/display_bins_generators.py
plotbin/display_pixels.py
plotbin/plot_velfield.py
plotbin/sauron_colormap.py
plotbin/symmetrize_velfield.py
plotbin-3.1.8.dist-info/licenses/LICENSE.txt
plotbin-3.1.8.dist-info/METADATA
plotbin-3.1.8.dist-info/WHEEL
plotbin-3.1.8.dist-info/top_level.txt
plotbin-3.1.8.dist-info/zip-safe
plotbin-3.1.8.dist-info/RECORD
